obsidian_mcp/__init__.py
obsidian_mcp/client.py
obsidian_mcp/server.py
obsidian_mcp/tools/__init__.py
obsidian_mcp/tools/base.py
obsidian_mcp/tools/canvas.py
obsidian_mcp/tools/files.py
obsidian_mcp/tools/patch.py
obsidian_mcp/tools/periodic.py
obsidian_mcp/tools/search.py
obsidian_api_mcp-0.1.5.dist-info/METADATA
obsidian_api_mcp-0.1.5.dist-info/WHEEL
obsidian_api_mcp-0.1.5.dist-info/entry_points.txt
obsidian_api_mcp-0.1.5.dist-info/licenses/LICENSE
obsidian_api_mcp-0.1.5.dist-info/RECORD
