Metadata-Version: 2.4
Name: obsidian-api-mcp
Version: 0.1.5
Summary: MCP server for Obsidian with full Canvas support
Project-URL: Homepage, https://github.com/ArtiPyHeart/obsidian-local-rest-api
Project-URL: Repository, https://github.com/ArtiPyHeart/obsidian-local-rest-api
Author-email: ArtiPyHeart <wwwyqy618@gmail.com>
License-Expression: MIT
License-File: LICENSE
Keywords: ai,canvas,claude,llm,mcp,obsidian
Classifier: Development Status :: 4 - Beta
Classifier: Intended Audience :: Developers
Classifier: License :: OSI Approved :: MIT License
Classifier: Programming Language :: Python :: 3
Classifier: Programming Language :: Python :: 3.11
Classifier: Programming Language :: Python :: 3.12
Classifier: Programming Language :: Python :: 3.13
Requires-Python: >=3.11
Requires-Dist: httpx>=0.27.0
Requires-Dist: mcp>=1.1.0
Requires-Dist: python-dotenv>=1.0.1
